mobiledetect/Mobile_Detect.json
mobiledetect/__init__.py
mobiledetect/detect.py
mobiledetect/version.py
mobiledetect/test/__init__.py
mobiledetect/test/test_user_agents.json
mobiledetect/test/test_user_agents.py
pymobiledetect-1.3.1.dist-info/DESCRIPTION.rst
pymobiledetect-1.3.1.dist-info/METADATA
pymobiledetect-1.3.1.dist-info/RECORD
pymobiledetect-1.3.1.dist-info/WHEEL
pymobiledetect-1.3.1.dist-info/metadata.json
pymobiledetect-1.3.1.dist-info/top_level.txt
